LLM_handler.py
__init__.py
email_handler.py
google_drive_handler.py
google_sheets_handler.py
job_processor.py
linkedin_handler.py
load_jobs.py
utils.py
AIJobApply-4.0.0.dist-info/LICENSE
AIJobApply-4.0.0.dist-info/METADATA
AIJobApply-4.0.0.dist-info/WHEEL
AIJobApply-4.0.0.dist-info/entry_points.txt
AIJobApply-4.0.0.dist-info/top_level.txt
AIJobApply-4.0.0.dist-info/RECORD
