Metadata-Version: 2.1
Name: AIJobApply
Version: 4.0.0
Summary: Package to apply for jobs automatically and send emails
Author-email: Sandeeppvn <sandeeppvn@gmail.com>
Project-URL: homepage, https://github.com/sandeeppvn/AIJobApply
Classifier: Programming Language :: Python :: 3
Classifier: Operating System :: OS Independent
License-File: LICENSE
Requires-Dist: ConfigParser
Requires-Dist: openai
Requires-Dist: pytest
Requires-Dist: python-dotenv
Requires-Dist: tqdm
Requires-Dist: requests
Requires-Dist: gspread
Requires-Dist: pandas
Requires-Dist: selenium
Requires-Dist: tk
Requires-Dist: langchain
Requires-Dist: validate-email
Requires-Dist: pydantic
Requires-Dist: gptrim
Requires-Dist: docxtpl
Requires-Dist: python-docx
Requires-Dist: google-api-python-client
Requires-Dist: flask
